bootify/__init__.py
bootify/loader.py
bootify-0.1.0.dist-info/licenses/LICENSE
bootify-0.1.0.dist-info/METADATA
bootify-0.1.0.dist-info/WHEEL
bootify-0.1.0.dist-info/top_level.txt
bootify-0.1.0.dist-info/RECORD
